jupyter_api/__init__.py
jupyter_api/client.py
jupyter_api_client-0.0.3.dist-info/LICENSE
jupyter_api_client-0.0.3.dist-info/METADATA
jupyter_api_client-0.0.3.dist-info/WHEEL
jupyter_api_client-0.0.3.dist-info/top_level.txt
jupyter_api_client-0.0.3.dist-info/RECORD
