Metadata-Version: 2.1
Name: jupyter-api-client
Version: 0.0.3
Summary: Unofficial Python API client for Jupyter
Home-page: https://github.com/tatsuiman/jupyter-api-client
Author: tatsuiman
License: UNKNOWN
Platform: UNKNOWN
Classifier: Programming Language :: Python :: 3
Classifier: License :: OSI Approved :: MIT License
Classifier: Operating System :: OS Independent
Requires-Python: >=3.5
Requires-Dist: requests
Requires-Dist: websocket-client
